aporiapy/__init__.py
aporiapy/main.py
aporiapy/compilers/__init__.py
aporiapy/compilers/compiler_01_sc.py
aporiapy/compilers/compiler_02_flat.py
aporiapy/compilers/compiler_03_cfi.py
aporiapy/compilers/utils.py
aporiapy-0.1.2.dist-info/METADATA
aporiapy-0.1.2.dist-info/WHEEL
aporiapy-0.1.2.dist-info/entry_points.txt
aporiapy-0.1.2.dist-info/top_level.txt
aporiapy-0.1.2.dist-info/RECORD
