Metadata-Version: 2.2
Name: aporiapy
Version: 0.1.2
Summary: A compiler which translates a subset of Python to the Aporia language
Author-email: Ephraim Siegfried <ephraim.siegfried@hotmail.com>
Requires-Python: >=3.10
Requires-Dist: aporia-interpreter>=0.1.2
